auto_ml/DataFrameVectorizer.py
auto_ml/__init__.py
auto_ml/_version.py
auto_ml/predictor.py
auto_ml/py_test.py
auto_ml/utils.py
auto_ml/utils_categorical_ensembling.py
auto_ml/utils_data_cleaning.py
auto_ml/utils_ensembling.py
auto_ml/utils_feature_selection.py
auto_ml/utils_model_training.py
auto_ml/utils_models.py
auto_ml/utils_scaling.py
auto_ml/utils_scoring.py
automl-2.9.9.dist-info/DESCRIPTION.rst
automl-2.9.9.dist-info/METADATA
automl-2.9.9.dist-info/RECORD
automl-2.9.9.dist-info/WHEEL
automl-2.9.9.dist-info/metadata.json
automl-2.9.9.dist-info/top_level.txt
