Metadata-Version: 2.0
Name: automl
Version: 2.9.9
Summary: Automated machine learning for production and analytics
Home-page: https://github.com/ClimbsRocks/auto_ml
Author: Preston Parry
Author-email: ClimbsBytes@gmail.com
License: MIT
Keywords: machine learning,data science,automated machine learning,regressor,regressors,regression,classification,classifiers,classifier,estimators,predictors,XGBoost,Random Forest,sklearn,scikit-learn,analytics,analysts,coefficients,feature importancesanalytics,artificial intelligence,subpredictors,ensembling,stacking,blending,feature engineering,feature extraction,feature selection,production,pandas,dataframes,machinejs,deep learning,tensorflow,deeplearning,lightgbm,gradient boosting,gbm,keras
Platform: UNKNOWN
Classifier: Development Status :: 5 - Production/Stable
Classifier: Intended Audience :: Developers
Classifier: Intended Audience :: Information Technology
Classifier: Intended Audience :: Science/Research
Classifier: Topic :: Scientific/Engineering :: Artificial Intelligence
Classifier: Topic :: Scientific/Engineering :: Information Analysis
Classifier: Topic :: Software Development :: Libraries :: Python Modules
Classifier: License :: OSI Approved :: MIT License
Classifier: Programming Language :: Python :: 2
Classifier: Programming Language :: Python :: 2.7
Classifier: Programming Language :: Python :: 3
Classifier: Programming Language :: Python :: 3.4
Classifier: Programming Language :: Python :: 3.4
Classifier: Programming Language :: Python :: 3.6
Requires-Dist: dill (<0.3,>=0.2.5)
Requires-Dist: h5py (<3.0,>=2.7.0)
Requires-Dist: lightgbm (<2.1,>=2.0.11)
Requires-Dist: numpy (<2.0,>=1.11.0)
Requires-Dist: pandas (<1.0,>=0.18.0)
Requires-Dist: pathos (<0.3.0,>=0.2.1)
Requires-Dist: python-dateutil (<3.0,>=2.6.1)
Requires-Dist: scikit-learn (<1.0,>=0.18.1)
Requires-Dist: scipy (<2.0,>=0.14.0)
Requires-Dist: sklearn-deap2 (<0.3,>=0.2.1)
Requires-Dist: tabulate (<1.0,>=0.7.5)
